gerotworldl/__init__.py
gerotworldl/connection.py
gerotworldl/downloader.py
gerotworldl/hash.py
gerotworldl/launcher.py
gerotworldl/mysql.py
gerotworldl/session.py
gerotworldl-0.0.1.dist-info/LICENSE
gerotworldl-0.0.1.dist-info/METADATA
gerotworldl-0.0.1.dist-info/WHEEL
gerotworldl-0.0.1.dist-info/top_level.txt
gerotworldl-0.0.1.dist-info/RECORD
