Metadata-Version: 2.1
Name: gerotworldl
Version: 0.0.1
Summary: library for gerotworld launcher
Author-email: nomfodm <nomfodm@gmail.com>
License: Copyright (c) 2018 The Python Packaging Authority        
Project-URL: Homepage, https://github.com/nomfodm
Project-URL: Bug Tracker, https://github.com/nomfodm
Classifier: Programming Language :: Python :: 3
Classifier: License :: OSI Approved :: MIT License
Classifier: Operating System :: OS Independent
Requires-Python: >=3.7
License-File: LICENSE
